nixthon/__init__.py
nixthon/main.py
nixthon/shell.nix
nixthon-0.1.0.dist-info/WHEEL
nixthon-0.1.0.dist-info/entry_points.txt
nixthon-0.1.0.dist-info/METADATA
nixthon-0.1.0.dist-info/RECORD
