Metadata-Version: 2.3
Name: nixthon
Version: 0.1.0
Summary: Add your description here
Author: Patarimi
Author-email: Patarimi <38954040+Patarimi@users.noreply.github.com>
Requires-Dist: cyclopts>=4.4.1
Requires-Python: >=3.12
